scansessiontool/__init__.py
scansessiontool/__main__.py
scansessiontool/__meta__.py
scansessiontool/dialogues.py
scansessiontool/help.txt
scansessiontool/scansessiontool.py
scansessiontool/sst.yaml
scansessiontool/sst_icon.ico
scansessiontool/sst_icon.png
scansessiontool/utilities.py
scansessiontool/widgets.py
ScanSessionTool-1.0.0.dist-info/COPYING.txt
ScanSessionTool-1.0.0.dist-info/METADATA
ScanSessionTool-1.0.0.dist-info/WHEEL
ScanSessionTool-1.0.0.dist-info/entry_points.txt
ScanSessionTool-1.0.0.dist-info/top_level.txt
ScanSessionTool-1.0.0.dist-info/RECORD
