Metadata-Version: 2.1
Name: ScanSessionTool
Version: 1.0.0
Summary: Scan Session Tool - A tool for (f)MRI scan session documentation and data archiving
Home-page: https://fladd.github.io/ScanSessionTool/
Author: Florian Krause, Nikos Kogias
Author-email: florian.krause@donders.ru.nl, nikos.kogias@donders.ru.nl
Classifier: Programming Language :: Python :: 3
Classifier: License :: OSI Approved :: GNU General Public License v3 (GPLv3)
Classifier: Operating System :: OS Independent
Requires-Python: >=3.6
License-File: COPYING.txt
Requires-Dist: pyYAML
Requires-Dist: pydicom
